README.rst
setup.py
AllureReportLibrary/AllureListener.py
AllureReportLibrary/AllureReportLibrary.py
AllureReportLibrary/__init__.py
AllureReportLibrary/common.py
AllureReportLibrary/constant.py
AllureReportLibrary/constants.py
AllureReportLibrary/rules.py
AllureReportLibrary/structure.py
AllureReportLibrary/utils.py
AllureReportLibrary/version.py
robotframework_allurereport.egg-info/PKG-INFO
robotframework_allurereport.egg-info/SOURCES.txt
robotframework_allurereport.egg-info/dependency_links.txt
robotframework_allurereport.egg-info/requires.txt
robotframework_allurereport.egg-info/top_level.txt