Metadata-Version: 1.1
Name: robotframework-allurereport
Version: 1.1.1
Summary: Allure Reporting Adaptor for Robot Framework
Home-page: https://github.com/kootstra/robotframework-allurereport
Author: Eltjona Qato, Anne Kootstra
Author-email: qatoeltjona@gmail.com, kootstra@hotmail.com
License: MIT License
Download-URL: https://github.com/kootstra/robotframework-allurereport/archive/1.1.1.tar.gz
Keywords: allure,robotframework,reporting
Platform: any
Classifier: License :: OSI Approved :: MIT License
Classifier: Operating System :: OS Independent
Classifier: Programming Language :: Python
Classifier: Topic :: Software Development :: Testing
Classifier: Development Status :: 4 - Beta
